pricestf_py/__init__.py
pricestf_py/pricestf.py
pricestf_py/tf2_item_qualities.py
pricestf_py/tf2_items.py
pricestf_py-0.1.2.dist-info/LICENSE
pricestf_py-0.1.2.dist-info/WHEEL
pricestf_py-0.1.2.dist-info/METADATA
pricestf_py-0.1.2.dist-info/RECORD
