Metadata-Version: 2.1
Name: pricestf_py
Version: 0.1.2
Summary: pricestf_py is a library to get Team Fortress 2 items' prices from prices.tf API.
Author-email: Nicolò Bordin <nicolofbordin@gmail.com>
Classifier: License :: OSI Approved :: MIT License
Project-URL: Home, https://github.com/nbordin/pricestf_py
